src/__init__.py
src/common.py
src/ipbot.py
src/ipcloud.py
src/ipfiles.py
src/ipmail.py
src/ipoci.py
src/ipsched.py
src/ipservice.py
src/ipsetup.py
src/protheus.py
protheus-0.0.3.dist-info/LICENSE
protheus-0.0.3.dist-info/METADATA
protheus-0.0.3.dist-info/WHEEL
protheus-0.0.3.dist-info/top_level.txt
protheus-0.0.3.dist-info/RECORD
