Metadata-Version: 2.1
Name: protheus
Version: 0.0.3
Summary: A command-line interface for helper managemente your environment Portheus
Home-page: https://github.com/HenriqueLuizz/protheus-cli
Author: Henrique Luiz
Author-email: henrique.luiz@totvs.com.br
License: UNKNOWN
Project-URL: Bug Reports, https://github.com/HenriqueLuizz/protheus-cli/issues
Project-URL: Say Thanks!, https://saythanks.io/to/henriqueluiz_silva%40yahoo.com.br
Project-URL: Source, https://github.com/HenriqueLuizz/protheus-cli
Platform: UNKNOWN
Classifier: Programming Language :: Python :: 3
Classifier: License :: OSI Approved :: MIT License
Classifier: Operating System :: OS Independent
Requires-Dist: schedule (~=0.6.0)
Requires-Dist: click (~=7.1.2)
